xhpubqt/__init__.py
xhpubqt/progresstip.py
xhpubqt/ue4slider.py
xhpubqt-0.0.2.dist-info/METADATA
xhpubqt-0.0.2.dist-info/WHEEL
xhpubqt-0.0.2.dist-info/top_level.txt
xhpubqt-0.0.2.dist-info/RECORD
