Metadata-Version: 2.1
Name: xhpubqt
Version: 0.0.2
Summary: a pub library for PyQt5 to implement some cool controls
Home-page: https://github.com/lamborghini1993/mypypi/tree/master/xhpubqt
Author: lamborghini1993
Author-email: 1323242382@qq.com
License: UNKNOWN
Platform: UNKNOWN
Classifier: Programming Language :: Python :: 3
Classifier: License :: OSI Approved :: MIT License
Classifier: Operating System :: OS Independent
Requires-Python: >=3.6
